tabor_control/__init__.py
tabor_control/device.py
tabor_control/util.py
tabor_control-0.1.1.dist-info/LICENSE
tabor_control-0.1.1.dist-info/METADATA
tabor_control-0.1.1.dist-info/WHEEL
tabor_control-0.1.1.dist-info/top_level.txt
tabor_control-0.1.1.dist-info/RECORD
