Metadata-Version: 2.1
Name: tabor-control
Version: 0.1.1
Summary: Small SCPI control interface for tabor awgs
Home-page: https://git-ce.rwth-aachen.de/simon.humpohl/tabor_control
Author: Simon Humpohl
Author-email: simon.humpohl@rwth-aachen.de
License: GPLv3
Keywords: hardware,awg,tabor,tabor electronics
Platform: UNKNOWN
Classifier: Programming Language :: Python :: 3
Classifier: Operating System :: OS Independent
Classifier: Topic :: Scientific/Engineering
Classifier: Intended Audience :: Science/Research
Classifier: License :: OSI Approved :: GNU General Public License v3 (GPLv3)
Requires-Python: >=3.6
License-File: LICENSE
Requires-Dist: pyvisa (>=1.11)
Requires-Dist: numpy
Requires-Dist: packaging
Requires-Dist: dataclasses
